mitmproxy_mcp/__init__.py
mitmproxy_mcp/flow_utils.py
mitmproxy_mcp/json_utils.py
mitmproxy_mcp/protection_analysis.py
mitmproxy_mcp/server.py
mseep_mitmproxy_mcp-0.1.4.dist-info/METADATA
mseep_mitmproxy_mcp-0.1.4.dist-info/WHEEL
mseep_mitmproxy_mcp-0.1.4.dist-info/entry_points.txt
mseep_mitmproxy_mcp-0.1.4.dist-info/top_level.txt
mseep_mitmproxy_mcp-0.1.4.dist-info/RECORD
