Metadata-Version: 2.4
Name: mseep-mitmproxy-mcp
Version: 0.1.4
Summary: A MCP server project
Author-email: mseep <support@skydeck.ai>
Requires-Python: >=3.11
Requires-Dist: mcp>=1.3.0
Requires-Dist: mitmproxy>=11.0.2
